cross_process_bridge/__init__.py
cross_process_bridge/child_process_bridge.py
cross_process_bridge/cross_process_bridge.py
cross_process_bridge/instance_creator.py
cross_process_bridge/models.py
cross_process_bridge-1.0.2.dist-info/METADATA
cross_process_bridge-1.0.2.dist-info/WHEEL
cross_process_bridge-1.0.2.dist-info/licenses/LICENSE
cross_process_bridge-1.0.2.dist-info/RECORD
