Metadata-Version: 2.1
Name: cross_process_bridge
Version: 1.0.2
Summary: Create an instance in a new process and call its functions seamlessly
Project-URL: Homepage, https://github.com/avraham-mayer/python-cross-process-bridge
Author-email: Avi Mayer <mayeravraham@gmail.com>
License-File: LICENSE
Classifier: License :: OSI Approved :: MIT License
Classifier: Operating System :: OS Independent
Classifier: Programming Language :: Python :: 3
Requires-Python: >=3.7
